tdt/APIStreamer.py
tdt/BH32.py
tdt/PynapseUDP.py
tdt/SynapseAPI.py
tdt/TDTUDP.py
tdt/TDTbin2py.py
tdt/TDTfilter.py
tdt/__init__.py
tdt-0.7.3.dist-info/LICENSE
tdt-0.7.3.dist-info/METADATA
tdt-0.7.3.dist-info/WHEEL
tdt-0.7.3.dist-info/top_level.txt
tdt-0.7.3.dist-info/RECORD
