Metadata-Version: 2.1
Name: tdt
Version: 0.7.3
Summary: Tucker-Davis Technologies (TDT) Python APIs for reading data and interacting with Synapse software
Home-page: UNKNOWN
Author: Mark Hanus
Author-email: mhanus@tdt.com
License: UNKNOWN
Platform: UNKNOWN
Requires-Dist: numpy
